paunchdir
tests
