Metadata-Version: 1.1
Name: paunch-dir
Version: 0.0.4
Summary: An algorithm to generate a path from file name which directory structure could store mass files
Home-page: https://github.com/starofrainnight/paunch-dir
Author: Hong-She Liang
Author-email: starofrainnight@gmail.com
License: Apache Software License
Keywords: paunchdir,paunch-dir
Platform: UNKNOWN
Classifier: Development Status :: 2 - Pre-Alpha
Classifier: Intended Audience :: Developers
Classifier: License :: OSI Approved :: Apache Software License
Classifier: Natural Language :: English
Classifier: Programming Language :: Python :: 3
Classifier: Programming Language :: Python :: 3.4
Classifier: Programming Language :: Python :: 3.5
Classifier: Programming Language :: Python :: 3.6
